investment_rebalancer/__init__.py
investment_rebalancer/controller/__init__.py
investment_rebalancer/controller/number_validator.py
investment_rebalancer/main.py
investment_rebalancer/model/__init__.py
investment_rebalancer/model/asset/__init__.py
investment_rebalancer/model/asset/etf.py
investment_rebalancer/model/classification/__init__.py
investment_rebalancer/model/classification/category.py
investment_rebalancer/model/classification/classification.py
investment_rebalancer/model/configuration.py
investment_rebalancer/model/errors.py
investment_rebalancer-1.0.1.dist-info/LICENSE
investment_rebalancer-1.0.1.dist-info/METADATA
investment_rebalancer-1.0.1.dist-info/WHEEL
investment_rebalancer-1.0.1.dist-info/entry_points.txt
investment_rebalancer-1.0.1.dist-info/RECORD
