Metadata-Version: 2.1
Name: investment-rebalancer
Version: 1.0.1
Summary: A simple tool helping you to calculate your portfolio rebalancing.
Home-page: https://github.com/Plebo13/investment-rebalancer
License: Apache-2.0
Author: Lukas Brauckmann
Author-email: lukas.brauckmann@gmail.com
Maintainer: Lukas Brauckmann
Maintainer-email: lukas.brauckmann@gmail.com
Requires-Python: >=3.10,<4.0
Classifier: License :: OSI Approved :: Apache Software License
Classifier: Operating System :: OS Independent
Classifier: Programming Language :: Python :: 3
Classifier: Programming Language :: Python :: 3.10
Classifier: Programming Language :: Python :: 3.11
Classifier: Programming Language :: Python :: 3.12
Requires-Dist: prettytable (>=3.8.0,<4.0.0)
Requires-Dist: prompt-toolkit (>=3.0.39,<4.0.0)
Requires-Dist: pydantic (>=2.6.3,<3.0.0)
Requires-Dist: sharepp (>=1.1.3,<2.0.0)
Project-URL: Repository, https://github.com/Plebo13/investment-rebalancer
